firecam/__init__.py
firecam/cmds/__init__.py
firecam/cmds/get_image_hpwren.py
firecam/cmds/sort_images.py
firecam/detection_policies/__init__.py
firecam/detection_policies/detect_always.py
firecam/detection_policies/detect_never.py
firecam/detection_policies/inception_and_threshold.py
firecam/detection_policies/policies.py
firecam/detection_policies/test_always_never.py
firecam/image_crop/__init__.py
firecam/image_crop/crop_single.py
firecam/image_crop/diff_nonSmoke.py
firecam/image_crop/gen_non_smoke.py
firecam/image_crop/recrop_min_size.py
firecam/image_crop/test_recrop_min_size.py
firecam/lib/__init__.py
firecam/lib/collect_args.py
firecam/lib/db_manager.py
firecam/lib/email_helper.py
firecam/lib/goog_helper.py
firecam/lib/img_archive.py
firecam/lib/rect_to_squares.py
firecam/lib/settings.py
firecam/lib/sms_helper.py
firecam/lib/test_collect_args.py
firecam/lib/tf_helper.py
oct_firecam-0.1.3.dist-info/AUTHORS
oct_firecam-0.1.3.dist-info/LICENSE
oct_firecam-0.1.3.dist-info/METADATA
oct_firecam-0.1.3.dist-info/WHEEL
oct_firecam-0.1.3.dist-info/entry_points.txt
oct_firecam-0.1.3.dist-info/top_level.txt
oct_firecam-0.1.3.dist-info/RECORD
