Metadata-Version: 2.1
Name: oct-firecam
Version: 0.1.3
Summary: Detect wildfires from camera images
Home-page: https://github.com/open-climate-tech/firecam
Author: Open Climate Tech
License: UNKNOWN
Platform: UNKNOWN
Classifier: Programming Language :: Python :: 3
Classifier: License :: OSI Approved :: Apache Software License
Classifier: Operating System :: OS Independent
Requires-Python: >=3.5
Requires-Dist: python-dateutil
Requires-Dist: requests
Requires-Dist: numpy
Requires-Dist: pillow
Requires-Dist: oauth2client
Requires-Dist: google-api-python-client
Requires-Dist: google-cloud-storage
Requires-Dist: google-cloud-pubsub
